{
    "99999999999948": "{{DVA_MOCK_URL}}/48",
    "99999999999949": "{{DVA_MOCK_URL}}/49",
    "99999999999950": "{{DVA_MOCK_URL}}/50",
    "99999999999951": "{{DVA_MOCK_URL}}/51",
    "99999999999961": "{{DVA_MOCK_URL}}/61",
    "99999999999963": "{{DVA_MOCK_URL}}/63",
    "99999999991001": "https://dva-inlog.interoplab.eu/ontwikkel/verplicht/oauth2/authorize",
    "99999999991002": "https://dva.interoplab.eu/ontwikkel/verplicht/oauth2/token",
    "99999999991047": "https://dva.interoplab.eu/ontwikkel/verplicht/fhir",
    "99999999991048": "https://dva.interoplab.eu/ontwikkel/verplicht/fhir",
    "99999999991049": "https://dva.interoplab.eu/ontwikkel/verplicht/fhir",
    "99999999991050": "https://dva.interoplab.eu/ontwikkel/verplicht/fhir",
    "99999999991051": "https://dva.interoplab.eu/ontwikkel/verplicht/fhir",
    "99999999991052": "https://dva.interoplab.eu/ontwikkel/verplicht/fhir",
    "99999999991053": "https://dva.interoplab.eu/ontwikkel/verplicht/fhir",
    "99999999991054": "https://dva.interoplab.eu/ontwikkel/verplicht/fhir",
    "99999999991061": "https://dva.interoplab.eu/ontwikkel/verplicht/fhir",
    "99999999991065": "https://dva.interoplab.eu/ontwikkel/verplicht/fhir",
    "99999999991066": "https://dva.interoplab.eu/ontwikkel/verplicht/fhir",
    "99999999991101": "https://dva.interoplab.eu/ontwikkel/verplicht/fhir",
    "99999999991102": "https://dva.interoplab.eu/ontwikkel/verplicht/fhir",
    "99999999991103": "https://dva.interoplab.eu/ontwikkel/verplicht/fhir",
    "99999999991104": "https://dva.interoplab.eu/ontwikkel/verplicht/fhir",
    "99999999991105": "https://dva.interoplab.eu/ontwikkel/verplicht/fhir",
    "99999999991106": "https://dva.interoplab.eu/ontwikkel/verplicht/fhir",
    "99999999991107": "https://dva.interoplab.eu/ontwikkel/verplicht/fhir",
    "99999999991108": "https://dva.interoplab.eu/ontwikkel/verplicht/fhir",
    "99999999991109": "https://dva.interoplab.eu/ontwikkel/verplicht/fhir",
    "99999999991110": "https://dva.interoplab.eu/ontwikkel/verplicht/fhir",
    "99999999991111": "https://dva.interoplab.eu/ontwikkel/verplicht/fhir",
    "99999999991112": "https://dva.interoplab.eu/ontwikkel/verplicht/fhir",
    "99999999991113": "https://dva.interoplab.eu/ontwikkel/verplicht/fhir",
    "999999999919000002": "https://dva.interoplab.eu/ontwikkel/verplicht/fhir",
    "999999999911000003": "https://dva.interoplab.eu/ontwikkel/verplicht/fhir"
}
